scrapy_xlsx/__init__.py
scrapy_xlsx/exporters.py
scrapy_xlsx-0.1.1.dist-info/LICENSE.txt
scrapy_xlsx-0.1.1.dist-info/METADATA
scrapy_xlsx-0.1.1.dist-info/WHEEL
scrapy_xlsx-0.1.1.dist-info/top_level.txt
scrapy_xlsx-0.1.1.dist-info/RECORD
