Metadata-Version: 1.1
Name: scrapy-xlsx
Version: 0.1.1
Summary: XLSX exporter for Scrapy
Home-page: https://github.com/jesuslosada/scrapy-xlsx
Author: Jesús Losada Novo
Author-email: dev@jesuslosada.com
License: MIT
Keywords: scrapy,xlsx,exporter
Platform: UNKNOWN
Classifier: Development Status :: 4 - Beta
Classifier: Intended Audience :: Developers
Classifier: License :: OSI Approved :: MIT License
Classifier: Natural Language :: English
Classifier: Operating System :: OS Independent
Classifier: Programming Language :: Python
Classifier: Programming Language :: Python :: 3
Classifier: Topic :: Software Development :: Libraries
